{
  "AltLookAngle": {
    "x": 0,
    "y": 0,
    "z": 0
  },
  "Autoraise": true,
  "Bag": {
    "Order": 0
  },
  "ColorDiffuse": {
    "b": 0,
    "g": 0.36652,
    "r": 0.70588
  },
  "ContainedObjects_order": [
    "Deck.20c269",
    "Custom_Tile.78827c",
    "Custom_Tile.5f46af",
    "CampaignBook.0cf9c7",
    "CardCustom.3d25c6",
    "Custom_Tile.c64617",
    "EncounterCards.0ac1dc",
    "OverviewCards.74971a",
    "OverviewCards.78cbcd",
    "OverviewCards.f1bd54",
    "OverviewCards.248eeb",
    "OverviewCards.2f7531",
    "OverviewCards.7e55f6"
  ],
  "ContainedObjects_path": "CampaignOnlyContent.5c483d",
  "Description": "",
  "DragSelectable": true,
  "GMNotes": "",
  "GUID": "5c483d",
  "Grid": true,
  "GridProjection": false,
  "Hands": false,
  "HideWhenFaceDown": false,
  "IgnoreFoW": false,
  "LayoutGroupSortIndex": 0,
  "Locked": true,
  "LuaScript": "",
  "LuaScriptState": "",
  "MaterialIndex": -1,
  "MeasureMovement": false,
  "MeshIndex": -1,
  "Name": "Bag",
  "Nickname": "Campaign Only Content",
  "Snap": true,
  "Sticky": true,
  "Tooltip": true,
  "Transform": {
    "posX": -36,
    "posY": 1.296,
    "posZ": 48.5,
    "rotX": 0,
    "rotY": 0,
    "rotZ": 0,
    "scaleX": 1,
    "scaleY": 1,
    "scaleZ": 1
  },
  "Value": 0,
  "XmlUI": ""
}
