{
  "AltLookAngle": {
    "x": 0,
    "y": 0,
    "z": 0
  },
  "Autoraise": true,
  "Bag": {
    "Order": 0
  },
  "ColorDiffuse": {
    "b": 0,
    "g": 0.36652,
    "r": 0.70588
  },
  "ContainedObjects_order": [
    "PlayerBoard.a30382",
    "RedArchaeologist.fb9f5d",
    "RedArchaeologist.9f84c9",
    "RedArchaeologist.e5b510",
    "Deck.d8547e",
    "Deck.52b0e5",
    "Deck.f682fb"
  ],
  "ContainedObjects_path": "SoloComponents.cabb5b",
  "Description": "",
  "DragSelectable": true,
  "GMNotes": "",
  "GUID": "cabb5b",
  "Grid": true,
  "GridProjection": false,
  "Hands": false,
  "HideWhenFaceDown": false,
  "IgnoreFoW": false,
  "LayoutGroupSortIndex": 0,
  "Locked": true,
  "LuaScript": "",
  "LuaScriptState": "",
  "MaterialIndex": -1,
  "MeasureMovement": false,
  "MeshIndex": -1,
  "Name": "Bag",
  "Nickname": "Solo Components",
  "Snap": true,
  "Sticky": true,
  "Tooltip": true,
  "Transform": {
    "posX": -44,
    "posY": 1.297,
    "posZ": 48.5,
    "rotX": 0,
    "rotY": 180,
    "rotZ": 0,
    "scaleX": 1,
    "scaleY": 1,
    "scaleZ": 1
  },
  "Value": 0,
  "XmlUI": ""
}
