{
  "AltLookAngle": {
    "x": 0,
    "y": 0,
    "z": 0
  },
  "Autoraise": true,
  "CardID": 7601,
  "ColorDiffuse": {
    "b": 0.71324,
    "g": 0.71324,
    "r": 0.71324
  },
  "CustomDeck": {
    "76": {
      "BackIsHidden": true,
      "BackURL": "http://cloud-3.steamusercontent.com/ugc/1862806463732171728/E2EBDA19EAF2265F39F3F36C197C7104CA4802E3/",
      "FaceURL": "http://cloud-3.steamusercontent.com/ugc/2496761664832837235/F8FBB919F48DA8E7EB94EB870CA29446A3E9F4F2/",
      "NumHeight": 3,
      "NumWidth": 2,
      "Type": 0,
      "UniqueBack": false
    }
  },
  "Description": "",
  "DragSelectable": true,
  "GMNotes_path": "AllCards.4bfea4/RepairedPlane.39129a.gmnotes",
  "GUID": "39129a",
  "Grid": true,
  "GridProjection": false,
  "Hands": true,
  "HideWhenFaceDown": true,
  "IgnoreFoW": false,
  "LayoutGroupSortIndex": 0,
  "Locked": false,
  "LuaScript": "",
  "LuaScriptState": "",
  "MeasureMovement": false,
  "Name": "Card",
  "Nickname": "Repaired Plane",
  "SidewaysCard": false,
  "Snap": true,
  "Sticky": true,
  "Tooltip": true,
  "Transform": {
    "posX": 67.443,
    "posY": 3.748,
    "posZ": -38.899,
    "rotX": 0,
    "rotY": 225,
    "rotZ": 0,
    "scaleX": 2.3,
    "scaleY": 1,
    "scaleZ": 2.3
  },
  "Value": 0,
  "XmlUI": ""
}
